{
  "domain": "www.radionrw.de",
  "normalizedDomain": "www.radionrw.de",
  "robotsTxt": "User-agent: *\nDisallow: \nDisallow: /assets/themes/yootheme/cache/\n\nHost: https://radionrw.de\n\n\n\n\n# This robots.txt file was created by Robots.txt Rewrite plugin: https://wordpress.org/plugins/robotstxt-rewrite/\n\nDisallow: /assets/uploads/bulk-media-register-tmp/\n\nSitemap: https://radionrw.de/xmlsitemap.xml\n\nAllow: /http://rsssitemap.xml\nAllow: /http://rsslatest.xml\nAllow: /http://htmlsitemap.htm\n\n",
  "globalRules": {
    "paths": {
      "allowed": [
        "/http://rsssitemap.xml",
        "/http://rsslatest.xml",
        "/http://htmlsitemap.htm"
      ],
      "disallowed": [
        "/assets/themes/yootheme/cache/",
        "/assets/uploads/bulk-media-register-tmp/"
      ]
    }
  },
  "specificBots": [],
  "stats": {
    "totalSpecificBots": 0,
    "allowedBots": 0,
    "disallowedBots": 0,
    "hasGlobalAllow": false
  },
  "bots": [
    {
      "name": "*",
      "allowed": false
    }
  ],
  "paths": {
    "allowed": [
      "/http://rsssitemap.xml",
      "/http://rsslatest.xml",
      "/http://htmlsitemap.htm"
    ],
    "disallowed": [
      "/assets/themes/yootheme/cache/",
      "/assets/uploads/bulk-media-register-tmp/"
    ]
  }
}