{
  "domain": "www.wochenspiegelonline.de",
  "normalizedDomain": "www.wochenspiegelonline.de",
  "robotsTxt": "User-Agent: *\nDisallow: /index.php?id=*\nDisallow: /typo3/\nDisallow: /fileadmin/\nDisallow: /kcs-test/*\nDisallow: /hene-test/*\n\nUser-Agent: Googlebot\nAllow: /news/\nAllow: /notdienst/\nAllow: /fileadmin/epaper/*\n\nUser-agent: Twitterbot\nAllow: /fileadmin/swvimportnews/media/*\n\nUser-Agent: SlySearch\nUser-Agent: SmartDownload\nUser-Agent: SpankBot\nUser-Agent: spanner\nUser-Agent: SuperBot\nUser-Agent: SuperHTTP\nUser-Agent: Surfbot\nUser-Agent: Lydia\nUser-Agent: Clearware\nUser-Agent: ShablastBot\nUser-Agent: BlitzBOT\nUser-Agent: claudebot\nUser-Agent: YandexBot\nUser-Agent: 2ip bot\nUser-Agent: Scrapy\nUser-Agent: DotBot\nUser-Agent: bingbot\nUser-Agent: OAI-SearchBot\nUser-Agent: SentiBot\nUser-Agent: MJ12bot\nDisallow: /\n\n",
  "globalRules": {
    "paths": {
      "allowed": [],
      "disallowed": [
        "/index.php?id=*",
        "/typo3/",
        "/fileadmin/",
        "/kcs-test/*",
        "/hene-test/*"
      ]
    }
  },
  "specificBots": [
    {
      "name": "Googlebot",
      "allowed": true,
      "paths": {
        "allowed": [
          "/news/",
          "/notdienst/",
          "/fileadmin/epaper/*"
        ],
        "disallowed": []
      }
    },
    {
      "name": "Twitterbot",
      "allowed": true,
      "paths": {
        "allowed": [
          "/fileadmin/swvimportnews/media/*"
        ],
        "disallowed": []
      }
    },
    {
      "name": "SlySearch",
      "allowed": false,
      "paths": {
        "allowed": [],
        "disallowed": []
      }
    },
    {
      "name": "SmartDownload",
      "allowed": false,
      "paths": {
        "allowed": [],
        "disallowed": []
      }
    },
    {
      "name": "SpankBot",
      "allowed": false,
      "paths": {
        "allowed": [],
        "disallowed": []
      }
    },
    {
      "name": "spanner",
      "allowed": false,
      "paths": {
        "allowed": [],
        "disallowed": []
      }
    },
    {
      "name": "SuperBot",
      "allowed": false,
      "paths": {
        "allowed": [],
        "disallowed": []
      }
    },
    {
      "name": "SuperHTTP",
      "allowed": false,
      "paths": {
        "allowed": [],
        "disallowed": []
      }
    },
    {
      "name": "Surfbot",
      "allowed": false,
      "paths": {
        "allowed": [],
        "disallowed": []
      }
    },
    {
      "name": "Lydia",
      "allowed": false,
      "paths": {
        "allowed": [],
        "disallowed": []
      }
    },
    {
      "name": "Clearware",
      "allowed": false,
      "paths": {
        "allowed": [],
        "disallowed": []
      }
    },
    {
      "name": "ShablastBot",
      "allowed": false,
      "paths": {
        "allowed": [],
        "disallowed": []
      }
    },
    {
      "name": "BlitzBOT",
      "allowed": false,
      "paths": {
        "allowed": [],
        "disallowed": []
      }
    },
    {
      "name": "claudebot",
      "allowed": false,
      "paths": {
        "allowed": [],
        "disallowed": []
      }
    },
    {
      "name": "YandexBot",
      "allowed": false,
      "paths": {
        "allowed": [],
        "disallowed": []
      }
    },
    {
      "name": "2ip bot",
      "allowed": false,
      "paths": {
        "allowed": [],
        "disallowed": []
      }
    },
    {
      "name": "Scrapy",
      "allowed": false,
      "paths": {
        "allowed": [],
        "disallowed": []
      }
    },
    {
      "name": "DotBot",
      "allowed": false,
      "paths": {
        "allowed": [],
        "disallowed": []
      }
    },
    {
      "name": "bingbot",
      "allowed": false,
      "paths": {
        "allowed": [],
        "disallowed": []
      }
    },
    {
      "name": "OAI-SearchBot",
      "allowed": false,
      "paths": {
        "allowed": [],
        "disallowed": []
      }
    },
    {
      "name": "SentiBot",
      "allowed": false,
      "paths": {
        "allowed": [],
        "disallowed": []
      }
    },
    {
      "name": "MJ12bot",
      "allowed": false,
      "paths": {
        "allowed": [],
        "disallowed": []
      }
    },
    {
      "name": "SlySearch",
      "allowed": false,
      "paths": {
        "allowed": [],
        "disallowed": []
      }
    },
    {
      "name": "SmartDownload",
      "allowed": false,
      "paths": {
        "allowed": [],
        "disallowed": []
      }
    },
    {
      "name": "SpankBot",
      "allowed": false,
      "paths": {
        "allowed": [],
        "disallowed": []
      }
    },
    {
      "name": "spanner",
      "allowed": false,
      "paths": {
        "allowed": [],
        "disallowed": []
      }
    },
    {
      "name": "SuperBot",
      "allowed": false,
      "paths": {
        "allowed": [],
        "disallowed": []
      }
    },
    {
      "name": "SuperHTTP",
      "allowed": false,
      "paths": {
        "allowed": [],
        "disallowed": []
      }
    },
    {
      "name": "Surfbot",
      "allowed": false,
      "paths": {
        "allowed": [],
        "disallowed": []
      }
    },
    {
      "name": "Lydia",
      "allowed": false,
      "paths": {
        "allowed": [],
        "disallowed": []
      }
    },
    {
      "name": "Clearware",
      "allowed": false,
      "paths": {
        "allowed": [],
        "disallowed": []
      }
    },
    {
      "name": "ShablastBot",
      "allowed": false,
      "paths": {
        "allowed": [],
        "disallowed": []
      }
    },
    {
      "name": "BlitzBOT",
      "allowed": false,
      "paths": {
        "allowed": [],
        "disallowed": []
      }
    },
    {
      "name": "claudebot",
      "allowed": false,
      "paths": {
        "allowed": [],
        "disallowed": []
      }
    },
    {
      "name": "YandexBot",
      "allowed": false,
      "paths": {
        "allowed": [],
        "disallowed": []
      }
    },
    {
      "name": "2ip bot",
      "allowed": false,
      "paths": {
        "allowed": [],
        "disallowed": []
      }
    },
    {
      "name": "Scrapy",
      "allowed": false,
      "paths": {
        "allowed": [],
        "disallowed": []
      }
    },
    {
      "name": "DotBot",
      "allowed": false,
      "paths": {
        "allowed": [],
        "disallowed": []
      }
    },
    {
      "name": "bingbot",
      "allowed": false,
      "paths": {
        "allowed": [],
        "disallowed": []
      }
    },
    {
      "name": "OAI-SearchBot",
      "allowed": false,
      "paths": {
        "allowed": [],
        "disallowed": []
      }
    },
    {
      "name": "SentiBot",
      "allowed": false,
      "paths": {
        "allowed": [],
        "disallowed": []
      }
    },
    {
      "name": "MJ12bot",
      "allowed": false,
      "paths": {
        "allowed": [],
        "disallowed": []
      }
    },
    {
      "name": "SlySearch",
      "allowed": false,
      "paths": {
        "allowed": [],
        "disallowed": []
      }
    },
    {
      "name": "SmartDownload",
      "allowed": false,
      "paths": {
        "allowed": [],
        "disallowed": []
      }
    },
    {
      "name": "SpankBot",
      "allowed": false,
      "paths": {
        "allowed": [],
        "disallowed": []
      }
    },
    {
      "name": "spanner",
      "allowed": false,
      "paths": {
        "allowed": [],
        "disallowed": []
      }
    },
    {
      "name": "SuperBot",
      "allowed": false,
      "paths": {
        "allowed": [],
        "disallowed": []
      }
    },
    {
      "name": "SuperHTTP",
      "allowed": false,
      "paths": {
        "allowed": [],
        "disallowed": []
      }
    },
    {
      "name": "Surfbot",
      "allowed": false,
      "paths": {
        "allowed": [],
        "disallowed": []
      }
    },
    {
      "name": "Lydia",
      "allowed": false,
      "paths": {
        "allowed": [],
        "disallowed": []
      }
    },
    {
      "name": "Clearware",
      "allowed": false,
      "paths": {
        "allowed": [],
        "disallowed": []
      }
    },
    {
      "name": "ShablastBot",
      "allowed": false,
      "paths": {
        "allowed": [],
        "disallowed": []
      }
    },
    {
      "name": "BlitzBOT",
      "allowed": false,
      "paths": {
        "allowed": [],
        "disallowed": []
      }
    },
    {
      "name": "claudebot",
      "allowed": false,
      "paths": {
        "allowed": [],
        "disallowed": []
      }
    },
    {
      "name": "YandexBot",
      "allowed": false,
      "paths": {
        "allowed": [],
        "disallowed": []
      }
    },
    {
      "name": "2ip bot",
      "allowed": false,
      "paths": {
        "allowed": [],
        "disallowed": []
      }
    },
    {
      "name": "Scrapy",
      "allowed": false,
      "paths": {
        "allowed": [],
        "disallowed": []
      }
    },
    {
      "name": "DotBot",
      "allowed": false,
      "paths": {
        "allowed": [],
        "disallowed": []
      }
    },
    {
      "name": "bingbot",
      "allowed": false,
      "paths": {
        "allowed": [],
        "disallowed": []
      }
    },
    {
      "name": "OAI-SearchBot",
      "allowed": false,
      "paths": {
        "allowed": [],
        "disallowed": []
      }
    },
    {
      "name": "SentiBot",
      "allowed": false,
      "paths": {
        "allowed": [],
        "disallowed": []
      }
    },
    {
      "name": "MJ12bot",
      "allowed": false,
      "paths": {
        "allowed": [],
        "disallowed": []
      }
    },
    {
      "name": "SlySearch",
      "allowed": false,
      "paths": {
        "allowed": [],
        "disallowed": []
      }
    },
    {
      "name": "SmartDownload",
      "allowed": false,
      "paths": {
        "allowed": [],
        "disallowed": []
      }
    },
    {
      "name": "SpankBot",
      "allowed": false,
      "paths": {
        "allowed": [],
        "disallowed": []
      }
    },
    {
      "name": "spanner",
      "allowed": false,
      "paths": {
        "allowed": [],
        "disallowed": []
      }
    },
    {
      "name": "SuperBot",
      "allowed": false,
      "paths": {
        "allowed": [],
        "disallowed": []
      }
    },
    {
      "name": "SuperHTTP",
      "allowed": false,
      "paths": {
        "allowed": [],
        "disallowed": []
      }
    },
    {
      "name": "Surfbot",
      "allowed": false,
      "paths": {
        "allowed": [],
        "disallowed": []
      }
    },
    {
      "name": "Lydia",
      "allowed": false,
      "paths": {
        "allowed": [],
        "disallowed": []
      }
    },
    {
      "name": "Clearware",
      "allowed": false,
      "paths": {
        "allowed": [],
        "disallowed": []
      }
    },
    {
      "name": "ShablastBot",
      "allowed": false,
      "paths": {
        "allowed": [],
        "disallowed": []
      }
    },
    {
      "name": "BlitzBOT",
      "allowed": false,
      "paths": {
        "allowed": [],
        "disallowed": []
      }
    },
    {
      "name": "claudebot",
      "allowed": false,
      "paths": {
        "allowed": [],
        "disallowed": []
      }
    },
    {
      "name": "YandexBot",
      "allowed": false,
      "paths": {
        "allowed": [],
        "disallowed": []
      }
    },
    {
      "name": "2ip bot",
      "allowed": false,
      "paths": {
        "allowed": [],
        "disallowed": []
      }
    },
    {
      "name": "Scrapy",
      "allowed": false,
      "paths": {
        "allowed": [],
        "disallowed": []
      }
    },
    {
      "name": "DotBot",
      "allowed": false,
      "paths": {
        "allowed": [],
        "disallowed": []
      }
    },
    {
      "name": "bingbot",
      "allowed": false,
      "paths": {
        "allowed": [],
        "disallowed": []
      }
    },
    {
      "name": "OAI-SearchBot",
      "allowed": false,
      "paths": {
        "allowed": [],
        "disallowed": []
      }
    },
    {
      "name": "SentiBot",
      "allowed": false,
      "paths": {
        "allowed": [],
        "disallowed": []
      }
    },
    {
      "name": "MJ12bot",
      "allowed": false,
      "paths": {
        "allowed": [],
        "disallowed": []
      }
    },
    {
      "name": "SlySearch",
      "allowed": false,
      "paths": {
        "allowed": [],
        "disallowed": []
      }
    },
    {
      "name": "SmartDownload",
      "allowed": false,
      "paths": {
        "allowed": [],
        "disallowed": []
      }
    },
    {
      "name": "SpankBot",
      "allowed": false,
      "paths": {
        "allowed": [],
        "disallowed": []
      }
    },
    {
      "name": "spanner",
      "allowed": false,
      "paths": {
        "allowed": [],
        "disallowed": []
      }
    },
    {
      "name": "SuperBot",
      "allowed": false,
      "paths": {
        "allowed": [],
        "disallowed": []
      }
    },
    {
      "name": "SuperHTTP",
      "allowed": false,
      "paths": {
        "allowed": [],
        "disallowed": []
      }
    },
    {
      "name": "Surfbot",
      "allowed": false,
      "paths": {
        "allowed": [],
        "disallowed": []
      }
    },
    {
      "name": "Lydia",
      "allowed": false,
      "paths": {
        "allowed": [],
        "disallowed": []
      }
    },
    {
      "name": "Clearware",
      "allowed": false,
      "paths": {
        "allowed": [],
        "disallowed": []
      }
    },
    {
      "name": "ShablastBot",
      "allowed": false,
      "paths": {
        "allowed": [],
        "disallowed": []
      }
    },
    {
      "name": "BlitzBOT",
      "allowed": false,
      "paths": {
        "allowed": [],
        "disallowed": []
      }
    },
    {
      "name": "claudebot",
      "allowed": false,
      "paths": {
        "allowed": [],
        "disallowed": []
      }
    },
    {
      "name": "YandexBot",
      "allowed": false,
      "paths": {
        "allowed": [],
        "disallowed": []
      }
    },
    {
      "name": "2ip bot",
      "allowed": false,
      "paths": {
        "allowed": [],
        "disallowed": []
      }
    },
    {
      "name": "Scrapy",
      "allowed": false,
      "paths": {
        "allowed": [],
        "disallowed": []
      }
    },
    {
      "name": "DotBot",
      "allowed": false,
      "paths": {
        "allowed": [],
        "disallowed": []
      }
    },
    {
      "name": "bingbot",
      "allowed": false,
      "paths": {
        "allowed": [],
        "disallowed": []
      }
    },
    {
      "name": "OAI-SearchBot",
      "allowed": false,
      "paths": {
        "allowed": [],
        "disallowed": []
      }
    },
    {
      "name": "SentiBot",
      "allowed": false,
      "paths": {
        "allowed": [],
        "disallowed": []
      }
    },
    {
      "name": "MJ12bot",
      "allowed": false,
      "paths": {
        "allowed": [],
        "disallowed": []
      }
    },
    {
      "name": "SlySearch",
      "allowed": false,
      "paths": {
        "allowed": [],
        "disallowed": []
      }
    },
    {
      "name": "SmartDownload",
      "allowed": false,
      "paths": {
        "allowed": [],
        "disallowed": []
      }
    },
    {
      "name": "SpankBot",
      "allowed": false,
      "paths": {
        "allowed": [],
        "disallowed": []
      }
    },
    {
      "name": "spanner",
      "allowed": false,
      "paths": {
        "allowed": [],
        "disallowed": []
      }
    },
    {
      "name": "SuperBot",
      "allowed": false,
      "paths": {
        "allowed": [],
        "disallowed": []
      }
    },
    {
      "name": "SuperHTTP",
      "allowed": false,
      "paths": {
        "allowed": [],
        "disallowed": []
      }
    },
    {
      "name": "Surfbot",
      "allowed": false,
      "paths": {
        "allowed": [],
        "disallowed": []
      }
    },
    {
      "name": "Lydia",
      "allowed": false,
      "paths": {
        "allowed": [],
        "disallowed": []
      }
    },
    {
      "name": "Clearware",
      "allowed": false,
      "paths": {
        "allowed": [],
        "disallowed": []
      }
    },
    {
      "name": "ShablastBot",
      "allowed": false,
      "paths": {
        "allowed": [],
        "disallowed": []
      }
    },
    {
      "name": "BlitzBOT",
      "allowed": false,
      "paths": {
        "allowed": [],
        "disallowed": []
      }
    },
    {
      "name": "claudebot",
      "allowed": false,
      "paths": {
        "allowed": [],
        "disallowed": []
      }
    },
    {
      "name": "YandexBot",
      "allowed": false,
      "paths": {
        "allowed": [],
        "disallowed": []
      }
    },
    {
      "name": "2ip bot",
      "allowed": false,
      "paths": {
        "allowed": [],
        "disallowed": []
      }
    },
    {
      "name": "Scrapy",
      "allowed": false,
      "paths": {
        "allowed": [],
        "disallowed": []
      }
    },
    {
      "name": "DotBot",
      "allowed": false,
      "paths": {
        "allowed": [],
        "disallowed": []
      }
    },
    {
      "name": "bingbot",
      "allowed": false,
      "paths": {
        "allowed": [],
        "disallowed": []
      }
    },
    {
      "name": "OAI-SearchBot",
      "allowed": false,
      "paths": {
        "allowed": [],
        "disallowed": []
      }
    },
    {
      "name": "SentiBot",
      "allowed": false,
      "paths": {
        "allowed": [],
        "disallowed": []
      }
    },
    {
      "name": "MJ12bot",
      "allowed": false,
      "paths": {
        "allowed": [],
        "disallowed": []
      }
    },
    {
      "name": "SlySearch",
      "allowed": false,
      "paths": {
        "allowed": [],
        "disallowed": []
      }
    },
    {
      "name": "SmartDownload",
      "allowed": false,
      "paths": {
        "allowed": [],
        "disallowed": []
      }
    },
    {
      "name": "SpankBot",
      "allowed": false,
      "paths": {
        "allowed": [],
        "disallowed": []
      }
    },
    {
      "name": "spanner",
      "allowed": false,
      "paths": {
        "allowed": [],
        "disallowed": []
      }
    },
    {
      "name": "SuperBot",
      "allowed": false,
      "paths": {
        "allowed": [],
        "disallowed": []
      }
    },
    {
      "name": "SuperHTTP",
      "allowed": false,
      "paths": {
        "allowed": [],
        "disallowed": []
      }
    },
    {
      "name": "Surfbot",
      "allowed": false,
      "paths": {
        "allowed": [],
        "disallowed": []
      }
    },
    {
      "name": "Lydia",
      "allowed": false,
      "paths": {
        "allowed": [],
        "disallowed": []
      }
    },
    {
      "name": "Clearware",
      "allowed": false,
      "paths": {
        "allowed": [],
        "disallowed": []
      }
    },
    {
      "name": "ShablastBot",
      "allowed": false,
      "paths": {
        "allowed": [],
        "disallowed": []
      }
    },
    {
      "name": "BlitzBOT",
      "allowed": false,
      "paths": {
        "allowed": [],
        "disallowed": []
      }
    },
    {
      "name": "claudebot",
      "allowed": false,
      "paths": {
        "allowed": [],
        "disallowed": []
      }
    },
    {
      "name": "YandexBot",
      "allowed": false,
      "paths": {
        "allowed": [],
        "disallowed": []
      }
    },
    {
      "name": "2ip bot",
      "allowed": false,
      "paths": {
        "allowed": [],
        "disallowed": []
      }
    },
    {
      "name": "Scrapy",
      "allowed": false,
      "paths": {
        "allowed": [],
        "disallowed": []
      }
    },
    {
      "name": "DotBot",
      "allowed": false,
      "paths": {
        "allowed": [],
        "disallowed": []
      }
    },
    {
      "name": "bingbot",
      "allowed": false,
      "paths": {
        "allowed": [],
        "disallowed": []
      }
    },
    {
      "name": "OAI-SearchBot",
      "allowed": false,
      "paths": {
        "allowed": [],
        "disallowed": []
      }
    },
    {
      "name": "SentiBot",
      "allowed": false,
      "paths": {
        "allowed": [],
        "disallowed": []
      }
    },
    {
      "name": "MJ12bot",
      "allowed": false,
      "paths": {
        "allowed": [],
        "disallowed": []
      }
    },
    {
      "name": "SlySearch",
      "allowed": false,
      "paths": {
        "allowed": [],
        "disallowed": []
      }
    },
    {
      "name": "SmartDownload",
      "allowed": false,
      "paths": {
        "allowed": [],
        "disallowed": []
      }
    },
    {
      "name": "SpankBot",
      "allowed": false,
      "paths": {
        "allowed": [],
        "disallowed": []
      }
    },
    {
      "name": "spanner",
      "allowed": false,
      "paths": {
        "allowed": [],
        "disallowed": []
      }
    },
    {
      "name": "SuperBot",
      "allowed": false,
      "paths": {
        "allowed": [],
        "disallowed": []
      }
    },
    {
      "name": "SuperHTTP",
      "allowed": false,
      "paths": {
        "allowed": [],
        "disallowed": []
      }
    },
    {
      "name": "Surfbot",
      "allowed": false,
      "paths": {
        "allowed": [],
        "disallowed": []
      }
    },
    {
      "name": "Lydia",
      "allowed": false,
      "paths": {
        "allowed": [],
        "disallowed": []
      }
    },
    {
      "name": "Clearware",
      "allowed": false,
      "paths": {
        "allowed": [],
        "disallowed": []
      }
    },
    {
      "name": "ShablastBot",
      "allowed": false,
      "paths": {
        "allowed": [],
        "disallowed": []
      }
    },
    {
      "name": "BlitzBOT",
      "allowed": false,
      "paths": {
        "allowed": [],
        "disallowed": []
      }
    },
    {
      "name": "claudebot",
      "allowed": false,
      "paths": {
        "allowed": [],
        "disallowed": []
      }
    },
    {
      "name": "YandexBot",
      "allowed": false,
      "paths": {
        "allowed": [],
        "disallowed": []
      }
    },
    {
      "name": "2ip bot",
      "allowed": false,
      "paths": {
        "allowed": [],
        "disallowed": []
      }
    },
    {
      "name": "Scrapy",
      "allowed": false,
      "paths": {
        "allowed": [],
        "disallowed": []
      }
    },
    {
      "name": "DotBot",
      "allowed": false,
      "paths": {
        "allowed": [],
        "disallowed": []
      }
    },
    {
      "name": "bingbot",
      "allowed": false,
      "paths": {
        "allowed": [],
        "disallowed": []
      }
    },
    {
      "name": "OAI-SearchBot",
      "allowed": false,
      "paths": {
        "allowed": [],
        "disallowed": []
      }
    },
    {
      "name": "SentiBot",
      "allowed": false,
      "paths": {
        "allowed": [],
        "disallowed": []
      }
    },
    {
      "name": "MJ12bot",
      "allowed": false,
      "paths": {
        "allowed": [],
        "disallowed": []
      }
    },
    {
      "name": "SlySearch",
      "allowed": false,
      "paths": {
        "allowed": [],
        "disallowed": []
      }
    },
    {
      "name": "SmartDownload",
      "allowed": false,
      "paths": {
        "allowed": [],
        "disallowed": []
      }
    },
    {
      "name": "SpankBot",
      "allowed": false,
      "paths": {
        "allowed": [],
        "disallowed": []
      }
    },
    {
      "name": "spanner",
      "allowed": false,
      "paths": {
        "allowed": [],
        "disallowed": []
      }
    },
    {
      "name": "SuperBot",
      "allowed": false,
      "paths": {
        "allowed": [],
        "disallowed": []
      }
    },
    {
      "name": "SuperHTTP",
      "allowed": false,
      "paths": {
        "allowed": [],
        "disallowed": []
      }
    },
    {
      "name": "Surfbot",
      "allowed": false,
      "paths": {
        "allowed": [],
        "disallowed": []
      }
    },
    {
      "name": "Lydia",
      "allowed": false,
      "paths": {
        "allowed": [],
        "disallowed": []
      }
    },
    {
      "name": "Clearware",
      "allowed": false,
      "paths": {
        "allowed": [],
        "disallowed": []
      }
    },
    {
      "name": "ShablastBot",
      "allowed": false,
      "paths": {
        "allowed": [],
        "disallowed": []
      }
    },
    {
      "name": "BlitzBOT",
      "allowed": false,
      "paths": {
        "allowed": [],
        "disallowed": []
      }
    },
    {
      "name": "claudebot",
      "allowed": false,
      "paths": {
        "allowed": [],
        "disallowed": []
      }
    },
    {
      "name": "YandexBot",
      "allowed": false,
      "paths": {
        "allowed": [],
        "disallowed": []
      }
    },
    {
      "name": "2ip bot",
      "allowed": false,
      "paths": {
        "allowed": [],
        "disallowed": []
      }
    },
    {
      "name": "Scrapy",
      "allowed": false,
      "paths": {
        "allowed": [],
        "disallowed": []
      }
    },
    {
      "name": "DotBot",
      "allowed": false,
      "paths": {
        "allowed": [],
        "disallowed": []
      }
    },
    {
      "name": "bingbot",
      "allowed": false,
      "paths": {
        "allowed": [],
        "disallowed": []
      }
    },
    {
      "name": "OAI-SearchBot",
      "allowed": false,
      "paths": {
        "allowed": [],
        "disallowed": []
      }
    },
    {
      "name": "SentiBot",
      "allowed": false,
      "paths": {
        "allowed": [],
        "disallowed": []
      }
    },
    {
      "name": "MJ12bot",
      "allowed": false,
      "paths": {
        "allowed": [],
        "disallowed": []
      }
    },
    {
      "name": "SlySearch",
      "allowed": false,
      "paths": {
        "allowed": [],
        "disallowed": []
      }
    },
    {
      "name": "SmartDownload",
      "allowed": false,
      "paths": {
        "allowed": [],
        "disallowed": []
      }
    },
    {
      "name": "SpankBot",
      "allowed": false,
      "paths": {
        "allowed": [],
        "disallowed": []
      }
    },
    {
      "name": "spanner",
      "allowed": false,
      "paths": {
        "allowed": [],
        "disallowed": []
      }
    },
    {
      "name": "SuperBot",
      "allowed": false,
      "paths": {
        "allowed": [],
        "disallowed": []
      }
    },
    {
      "name": "SuperHTTP",
      "allowed": false,
      "paths": {
        "allowed": [],
        "disallowed": []
      }
    },
    {
      "name": "Surfbot",
      "allowed": false,
      "paths": {
        "allowed": [],
        "disallowed": []
      }
    },
    {
      "name": "Lydia",
      "allowed": false,
      "paths": {
        "allowed": [],
        "disallowed": []
      }
    },
    {
      "name": "Clearware",
      "allowed": false,
      "paths": {
        "allowed": [],
        "disallowed": []
      }
    },
    {
      "name": "ShablastBot",
      "allowed": false,
      "paths": {
        "allowed": [],
        "disallowed": []
      }
    },
    {
      "name": "BlitzBOT",
      "allowed": false,
      "paths": {
        "allowed": [],
        "disallowed": []
      }
    },
    {
      "name": "claudebot",
      "allowed": false,
      "paths": {
        "allowed": [],
        "disallowed": []
      }
    },
    {
      "name": "YandexBot",
      "allowed": false,
      "paths": {
        "allowed": [],
        "disallowed": []
      }
    },
    {
      "name": "2ip bot",
      "allowed": false,
      "paths": {
        "allowed": [],
        "disallowed": []
      }
    },
    {
      "name": "Scrapy",
      "allowed": false,
      "paths": {
        "allowed": [],
        "disallowed": []
      }
    },
    {
      "name": "DotBot",
      "allowed": false,
      "paths": {
        "allowed": [],
        "disallowed": []
      }
    },
    {
      "name": "bingbot",
      "allowed": false,
      "paths": {
        "allowed": [],
        "disallowed": []
      }
    },
    {
      "name": "OAI-SearchBot",
      "allowed": false,
      "paths": {
        "allowed": [],
        "disallowed": []
      }
    },
    {
      "name": "SentiBot",
      "allowed": false,
      "paths": {
        "allowed": [],
        "disallowed": []
      }
    },
    {
      "name": "MJ12bot",
      "allowed": false,
      "paths": {
        "allowed": [],
        "disallowed": []
      }
    },
    {
      "name": "SlySearch",
      "allowed": false,
      "paths": {
        "allowed": [],
        "disallowed": []
      }
    },
    {
      "name": "SmartDownload",
      "allowed": false,
      "paths": {
        "allowed": [],
        "disallowed": []
      }
    },
    {
      "name": "SpankBot",
      "allowed": false,
      "paths": {
        "allowed": [],
        "disallowed": []
      }
    },
    {
      "name": "spanner",
      "allowed": false,
      "paths": {
        "allowed": [],
        "disallowed": []
      }
    },
    {
      "name": "SuperBot",
      "allowed": false,
      "paths": {
        "allowed": [],
        "disallowed": []
      }
    },
    {
      "name": "SuperHTTP",
      "allowed": false,
      "paths": {
        "allowed": [],
        "disallowed": []
      }
    },
    {
      "name": "Surfbot",
      "allowed": false,
      "paths": {
        "allowed": [],
        "disallowed": []
      }
    },
    {
      "name": "Lydia",
      "allowed": false,
      "paths": {
        "allowed": [],
        "disallowed": []
      }
    },
    {
      "name": "Clearware",
      "allowed": false,
      "paths": {
        "allowed": [],
        "disallowed": []
      }
    },
    {
      "name": "ShablastBot",
      "allowed": false,
      "paths": {
        "allowed": [],
        "disallowed": []
      }
    },
    {
      "name": "BlitzBOT",
      "allowed": false,
      "paths": {
        "allowed": [],
        "disallowed": []
      }
    },
    {
      "name": "claudebot",
      "allowed": false,
      "paths": {
        "allowed": [],
        "disallowed": []
      }
    },
    {
      "name": "YandexBot",
      "allowed": false,
      "paths": {
        "allowed": [],
        "disallowed": []
      }
    },
    {
      "name": "2ip bot",
      "allowed": false,
      "paths": {
        "allowed": [],
        "disallowed": []
      }
    },
    {
      "name": "Scrapy",
      "allowed": false,
      "paths": {
        "allowed": [],
        "disallowed": []
      }
    },
    {
      "name": "DotBot",
      "allowed": false,
      "paths": {
        "allowed": [],
        "disallowed": []
      }
    },
    {
      "name": "bingbot",
      "allowed": false,
      "paths": {
        "allowed": [],
        "disallowed": []
      }
    },
    {
      "name": "OAI-SearchBot",
      "allowed": false,
      "paths": {
        "allowed": [],
        "disallowed": []
      }
    },
    {
      "name": "SentiBot",
      "allowed": false,
      "paths": {
        "allowed": [],
        "disallowed": []
      }
    },
    {
      "name": "MJ12bot",
      "allowed": false,
      "paths": {
        "allowed": [],
        "disallowed": []
      }
    },
    {
      "name": "SlySearch",
      "allowed": false,
      "paths": {
        "allowed": [],
        "disallowed": []
      }
    },
    {
      "name": "SmartDownload",
      "allowed": false,
      "paths": {
        "allowed": [],
        "disallowed": []
      }
    },
    {
      "name": "SpankBot",
      "allowed": false,
      "paths": {
        "allowed": [],
        "disallowed": []
      }
    },
    {
      "name": "spanner",
      "allowed": false,
      "paths": {
        "allowed": [],
        "disallowed": []
      }
    },
    {
      "name": "SuperBot",
      "allowed": false,
      "paths": {
        "allowed": [],
        "disallowed": []
      }
    },
    {
      "name": "SuperHTTP",
      "allowed": false,
      "paths": {
        "allowed": [],
        "disallowed": []
      }
    },
    {
      "name": "Surfbot",
      "allowed": false,
      "paths": {
        "allowed": [],
        "disallowed": []
      }
    },
    {
      "name": "Lydia",
      "allowed": false,
      "paths": {
        "allowed": [],
        "disallowed": []
      }
    },
    {
      "name": "Clearware",
      "allowed": false,
      "paths": {
        "allowed": [],
        "disallowed": []
      }
    },
    {
      "name": "ShablastBot",
      "allowed": false,
      "paths": {
        "allowed": [],
        "disallowed": []
      }
    },
    {
      "name": "BlitzBOT",
      "allowed": false,
      "paths": {
        "allowed": [],
        "disallowed": []
      }
    },
    {
      "name": "claudebot",
      "allowed": false,
      "paths": {
        "allowed": [],
        "disallowed": []
      }
    },
    {
      "name": "YandexBot",
      "allowed": false,
      "paths": {
        "allowed": [],
        "disallowed": []
      }
    },
    {
      "name": "2ip bot",
      "allowed": false,
      "paths": {
        "allowed": [],
        "disallowed": []
      }
    },
    {
      "name": "Scrapy",
      "allowed": false,
      "paths": {
        "allowed": [],
        "disallowed": []
      }
    },
    {
      "name": "DotBot",
      "allowed": false,
      "paths": {
        "allowed": [],
        "disallowed": []
      }
    },
    {
      "name": "bingbot",
      "allowed": false,
      "paths": {
        "allowed": [],
        "disallowed": []
      }
    },
    {
      "name": "OAI-SearchBot",
      "allowed": false,
      "paths": {
        "allowed": [],
        "disallowed": []
      }
    },
    {
      "name": "SentiBot",
      "allowed": false,
      "paths": {
        "allowed": [],
        "disallowed": []
      }
    },
    {
      "name": "MJ12bot",
      "allowed": false,
      "paths": {
        "allowed": [],
        "disallowed": []
      }
    },
    {
      "name": "SlySearch",
      "allowed": false,
      "paths": {
        "allowed": [],
        "disallowed": []
      }
    },
    {
      "name": "SmartDownload",
      "allowed": false,
      "paths": {
        "allowed": [],
        "disallowed": []
      }
    },
    {
      "name": "SpankBot",
      "allowed": false,
      "paths": {
        "allowed": [],
        "disallowed": []
      }
    },
    {
      "name": "spanner",
      "allowed": false,
      "paths": {
        "allowed": [],
        "disallowed": []
      }
    },
    {
      "name": "SuperBot",
      "allowed": false,
      "paths": {
        "allowed": [],
        "disallowed": []
      }
    },
    {
      "name": "SuperHTTP",
      "allowed": false,
      "paths": {
        "allowed": [],
        "disallowed": []
      }
    },
    {
      "name": "Surfbot",
      "allowed": false,
      "paths": {
        "allowed": [],
        "disallowed": []
      }
    },
    {
      "name": "Lydia",
      "allowed": false,
      "paths": {
        "allowed": [],
        "disallowed": []
      }
    },
    {
      "name": "Clearware",
      "allowed": false,
      "paths": {
        "allowed": [],
        "disallowed": []
      }
    },
    {
      "name": "ShablastBot",
      "allowed": false,
      "paths": {
        "allowed": [],
        "disallowed": []
      }
    },
    {
      "name": "BlitzBOT",
      "allowed": false,
      "paths": {
        "allowed": [],
        "disallowed": []
      }
    },
    {
      "name": "claudebot",
      "allowed": false,
      "paths": {
        "allowed": [],
        "disallowed": []
      }
    },
    {
      "name": "YandexBot",
      "allowed": false,
      "paths": {
        "allowed": [],
        "disallowed": []
      }
    },
    {
      "name": "2ip bot",
      "allowed": false,
      "paths": {
        "allowed": [],
        "disallowed": []
      }
    },
    {
      "name": "Scrapy",
      "allowed": false,
      "paths": {
        "allowed": [],
        "disallowed": []
      }
    },
    {
      "name": "DotBot",
      "allowed": false,
      "paths": {
        "allowed": [],
        "disallowed": []
      }
    },
    {
      "name": "bingbot",
      "allowed": false,
      "paths": {
        "allowed": [],
        "disallowed": []
      }
    },
    {
      "name": "OAI-SearchBot",
      "allowed": false,
      "paths": {
        "allowed": [],
        "disallowed": []
      }
    },
    {
      "name": "SentiBot",
      "allowed": false,
      "paths": {
        "allowed": [],
        "disallowed": []
      }
    },
    {
      "name": "MJ12bot",
      "allowed": false,
      "paths": {
        "allowed": [],
        "disallowed": []
      }
    },
    {
      "name": "SlySearch",
      "allowed": false,
      "paths": {
        "allowed": [],
        "disallowed": []
      }
    },
    {
      "name": "SmartDownload",
      "allowed": false,
      "paths": {
        "allowed": [],
        "disallowed": []
      }
    },
    {
      "name": "SpankBot",
      "allowed": false,
      "paths": {
        "allowed": [],
        "disallowed": []
      }
    },
    {
      "name": "spanner",
      "allowed": false,
      "paths": {
        "allowed": [],
        "disallowed": []
      }
    },
    {
      "name": "SuperBot",
      "allowed": false,
      "paths": {
        "allowed": [],
        "disallowed": []
      }
    },
    {
      "name": "SuperHTTP",
      "allowed": false,
      "paths": {
        "allowed": [],
        "disallowed": []
      }
    },
    {
      "name": "Surfbot",
      "allowed": false,
      "paths": {
        "allowed": [],
        "disallowed": []
      }
    },
    {
      "name": "Lydia",
      "allowed": false,
      "paths": {
        "allowed": [],
        "disallowed": []
      }
    },
    {
      "name": "Clearware",
      "allowed": false,
      "paths": {
        "allowed": [],
        "disallowed": []
      }
    },
    {
      "name": "ShablastBot",
      "allowed": false,
      "paths": {
        "allowed": [],
        "disallowed": []
      }
    },
    {
      "name": "BlitzBOT",
      "allowed": false,
      "paths": {
        "allowed": [],
        "disallowed": []
      }
    },
    {
      "name": "claudebot",
      "allowed": false,
      "paths": {
        "allowed": [],
        "disallowed": []
      }
    },
    {
      "name": "YandexBot",
      "allowed": false,
      "paths": {
        "allowed": [],
        "disallowed": []
      }
    },
    {
      "name": "2ip bot",
      "allowed": false,
      "paths": {
        "allowed": [],
        "disallowed": []
      }
    },
    {
      "name": "Scrapy",
      "allowed": false,
      "paths": {
        "allowed": [],
        "disallowed": []
      }
    },
    {
      "name": "DotBot",
      "allowed": false,
      "paths": {
        "allowed": [],
        "disallowed": []
      }
    },
    {
      "name": "bingbot",
      "allowed": false,
      "paths": {
        "allowed": [],
        "disallowed": []
      }
    },
    {
      "name": "OAI-SearchBot",
      "allowed": false,
      "paths": {
        "allowed": [],
        "disallowed": []
      }
    },
    {
      "name": "SentiBot",
      "allowed": false,
      "paths": {
        "allowed": [],
        "disallowed": []
      }
    },
    {
      "name": "MJ12bot",
      "allowed": false,
      "paths": {
        "allowed": [],
        "disallowed": []
      }
    },
    {
      "name": "SlySearch",
      "allowed": false,
      "paths": {
        "allowed": [],
        "disallowed": []
      }
    },
    {
      "name": "SmartDownload",
      "allowed": false,
      "paths": {
        "allowed": [],
        "disallowed": []
      }
    },
    {
      "name": "SpankBot",
      "allowed": false,
      "paths": {
        "allowed": [],
        "disallowed": []
      }
    },
    {
      "name": "spanner",
      "allowed": false,
      "paths": {
        "allowed": [],
        "disallowed": []
      }
    },
    {
      "name": "SuperBot",
      "allowed": false,
      "paths": {
        "allowed": [],
        "disallowed": []
      }
    },
    {
      "name": "SuperHTTP",
      "allowed": false,
      "paths": {
        "allowed": [],
        "disallowed": []
      }
    },
    {
      "name": "Surfbot",
      "allowed": false,
      "paths": {
        "allowed": [],
        "disallowed": []
      }
    },
    {
      "name": "Lydia",
      "allowed": false,
      "paths": {
        "allowed": [],
        "disallowed": []
      }
    },
    {
      "name": "Clearware",
      "allowed": false,
      "paths": {
        "allowed": [],
        "disallowed": []
      }
    },
    {
      "name": "ShablastBot",
      "allowed": false,
      "paths": {
        "allowed": [],
        "disallowed": []
      }
    },
    {
      "name": "BlitzBOT",
      "allowed": false,
      "paths": {
        "allowed": [],
        "disallowed": []
      }
    },
    {
      "name": "claudebot",
      "allowed": false,
      "paths": {
        "allowed": [],
        "disallowed": []
      }
    },
    {
      "name": "YandexBot",
      "allowed": false,
      "paths": {
        "allowed": [],
        "disallowed": []
      }
    },
    {
      "name": "2ip bot",
      "allowed": false,
      "paths": {
        "allowed": [],
        "disallowed": []
      }
    },
    {
      "name": "Scrapy",
      "allowed": false,
      "paths": {
        "allowed": [],
        "disallowed": []
      }
    },
    {
      "name": "DotBot",
      "allowed": false,
      "paths": {
        "allowed": [],
        "disallowed": []
      }
    },
    {
      "name": "bingbot",
      "allowed": false,
      "paths": {
        "allowed": [],
        "disallowed": []
      }
    },
    {
      "name": "OAI-SearchBot",
      "allowed": false,
      "paths": {
        "allowed": [],
        "disallowed": []
      }
    },
    {
      "name": "SentiBot",
      "allowed": false,
      "paths": {
        "allowed": [],
        "disallowed": []
      }
    },
    {
      "name": "MJ12bot",
      "allowed": false,
      "paths": {
        "allowed": [],
        "disallowed": []
      }
    },
    {
      "name": "SlySearch",
      "allowed": false,
      "paths": {
        "allowed": [],
        "disallowed": []
      }
    },
    {
      "name": "SmartDownload",
      "allowed": false,
      "paths": {
        "allowed": [],
        "disallowed": []
      }
    },
    {
      "name": "SpankBot",
      "allowed": false,
      "paths": {
        "allowed": [],
        "disallowed": []
      }
    },
    {
      "name": "spanner",
      "allowed": false,
      "paths": {
        "allowed": [],
        "disallowed": []
      }
    },
    {
      "name": "SuperBot",
      "allowed": false,
      "paths": {
        "allowed": [],
        "disallowed": []
      }
    },
    {
      "name": "SuperHTTP",
      "allowed": false,
      "paths": {
        "allowed": [],
        "disallowed": []
      }
    },
    {
      "name": "Surfbot",
      "allowed": false,
      "paths": {
        "allowed": [],
        "disallowed": []
      }
    },
    {
      "name": "Lydia",
      "allowed": false,
      "paths": {
        "allowed": [],
        "disallowed": []
      }
    },
    {
      "name": "Clearware",
      "allowed": false,
      "paths": {
        "allowed": [],
        "disallowed": []
      }
    },
    {
      "name": "ShablastBot",
      "allowed": false,
      "paths": {
        "allowed": [],
        "disallowed": []
      }
    },
    {
      "name": "BlitzBOT",
      "allowed": false,
      "paths": {
        "allowed": [],
        "disallowed": []
      }
    },
    {
      "name": "claudebot",
      "allowed": false,
      "paths": {
        "allowed": [],
        "disallowed": []
      }
    },
    {
      "name": "YandexBot",
      "allowed": false,
      "paths": {
        "allowed": [],
        "disallowed": []
      }
    },
    {
      "name": "2ip bot",
      "allowed": false,
      "paths": {
        "allowed": [],
        "disallowed": []
      }
    },
    {
      "name": "Scrapy",
      "allowed": false,
      "paths": {
        "allowed": [],
        "disallowed": []
      }
    },
    {
      "name": "DotBot",
      "allowed": false,
      "paths": {
        "allowed": [],
        "disallowed": []
      }
    },
    {
      "name": "bingbot",
      "allowed": false,
      "paths": {
        "allowed": [],
        "disallowed": []
      }
    },
    {
      "name": "OAI-SearchBot",
      "allowed": false,
      "paths": {
        "allowed": [],
        "disallowed": []
      }
    },
    {
      "name": "SentiBot",
      "allowed": false,
      "paths": {
        "allowed": [],
        "disallowed": []
      }
    },
    {
      "name": "MJ12bot",
      "allowed": false,
      "paths": {
        "allowed": [],
        "disallowed": []
      }
    },
    {
      "name": "SlySearch",
      "allowed": false,
      "paths": {
        "allowed": [],
        "disallowed": []
      }
    },
    {
      "name": "SmartDownload",
      "allowed": false,
      "paths": {
        "allowed": [],
        "disallowed": []
      }
    },
    {
      "name": "SpankBot",
      "allowed": false,
      "paths": {
        "allowed": [],
        "disallowed": []
      }
    },
    {
      "name": "spanner",
      "allowed": false,
      "paths": {
        "allowed": [],
        "disallowed": []
      }
    },
    {
      "name": "SuperBot",
      "allowed": false,
      "paths": {
        "allowed": [],
        "disallowed": []
      }
    },
    {
      "name": "SuperHTTP",
      "allowed": false,
      "paths": {
        "allowed": [],
        "disallowed": []
      }
    },
    {
      "name": "Surfbot",
      "allowed": false,
      "paths": {
        "allowed": [],
        "disallowed": []
      }
    },
    {
      "name": "Lydia",
      "allowed": false,
      "paths": {
        "allowed": [],
        "disallowed": []
      }
    },
    {
      "name": "Clearware",
      "allowed": false,
      "paths": {
        "allowed": [],
        "disallowed": []
      }
    },
    {
      "name": "ShablastBot",
      "allowed": false,
      "paths": {
        "allowed": [],
        "disallowed": []
      }
    },
    {
      "name": "BlitzBOT",
      "allowed": false,
      "paths": {
        "allowed": [],
        "disallowed": []
      }
    },
    {
      "name": "claudebot",
      "allowed": false,
      "paths": {
        "allowed": [],
        "disallowed": []
      }
    },
    {
      "name": "YandexBot",
      "allowed": false,
      "paths": {
        "allowed": [],
        "disallowed": []
      }
    },
    {
      "name": "2ip bot",
      "allowed": false,
      "paths": {
        "allowed": [],
        "disallowed": []
      }
    },
    {
      "name": "Scrapy",
      "allowed": false,
      "paths": {
        "allowed": [],
        "disallowed": []
      }
    },
    {
      "name": "DotBot",
      "allowed": false,
      "paths": {
        "allowed": [],
        "disallowed": []
      }
    },
    {
      "name": "bingbot",
      "allowed": false,
      "paths": {
        "allowed": [],
        "disallowed": []
      }
    },
    {
      "name": "OAI-SearchBot",
      "allowed": false,
      "paths": {
        "allowed": [],
        "disallowed": []
      }
    },
    {
      "name": "SentiBot",
      "allowed": false,
      "paths": {
        "allowed": [],
        "disallowed": []
      }
    },
    {
      "name": "MJ12bot",
      "allowed": false,
      "paths": {
        "allowed": [],
        "disallowed": []
      }
    },
    {
      "name": "SlySearch",
      "allowed": false,
      "paths": {
        "allowed": [],
        "disallowed": []
      }
    },
    {
      "name": "SmartDownload",
      "allowed": false,
      "paths": {
        "allowed": [],
        "disallowed": []
      }
    },
    {
      "name": "SpankBot",
      "allowed": false,
      "paths": {
        "allowed": [],
        "disallowed": []
      }
    },
    {
      "name": "spanner",
      "allowed": false,
      "paths": {
        "allowed": [],
        "disallowed": []
      }
    },
    {
      "name": "SuperBot",
      "allowed": false,
      "paths": {
        "allowed": [],
        "disallowed": []
      }
    },
    {
      "name": "SuperHTTP",
      "allowed": false,
      "paths": {
        "allowed": [],
        "disallowed": []
      }
    },
    {
      "name": "Surfbot",
      "allowed": false,
      "paths": {
        "allowed": [],
        "disallowed": []
      }
    },
    {
      "name": "Lydia",
      "allowed": false,
      "paths": {
        "allowed": [],
        "disallowed": []
      }
    },
    {
      "name": "Clearware",
      "allowed": false,
      "paths": {
        "allowed": [],
        "disallowed": []
      }
    },
    {
      "name": "ShablastBot",
      "allowed": false,
      "paths": {
        "allowed": [],
        "disallowed": []
      }
    },
    {
      "name": "BlitzBOT",
      "allowed": false,
      "paths": {
        "allowed": [],
        "disallowed": []
      }
    },
    {
      "name": "claudebot",
      "allowed": false,
      "paths": {
        "allowed": [],
        "disallowed": []
      }
    },
    {
      "name": "YandexBot",
      "allowed": false,
      "paths": {
        "allowed": [],
        "disallowed": []
      }
    },
    {
      "name": "2ip bot",
      "allowed": false,
      "paths": {
        "allowed": [],
        "disallowed": []
      }
    },
    {
      "name": "Scrapy",
      "allowed": false,
      "paths": {
        "allowed": [],
        "disallowed": []
      }
    },
    {
      "name": "DotBot",
      "allowed": false,
      "paths": {
        "allowed": [],
        "disallowed": []
      }
    },
    {
      "name": "bingbot",
      "allowed": false,
      "paths": {
        "allowed": [],
        "disallowed": []
      }
    },
    {
      "name": "OAI-SearchBot",
      "allowed": false,
      "paths": {
        "allowed": [],
        "disallowed": []
      }
    },
    {
      "name": "SentiBot",
      "allowed": false,
      "paths": {
        "allowed": [],
        "disallowed": []
      }
    },
    {
      "name": "MJ12bot",
      "allowed": false,
      "paths": {
        "allowed": [],
        "disallowed": []
      }
    },
    {
      "name": "SlySearch",
      "allowed": false,
      "paths": {
        "allowed": [],
        "disallowed": []
      }
    },
    {
      "name": "SmartDownload",
      "allowed": false,
      "paths": {
        "allowed": [],
        "disallowed": []
      }
    },
    {
      "name": "SpankBot",
      "allowed": false,
      "paths": {
        "allowed": [],
        "disallowed": []
      }
    },
    {
      "name": "spanner",
      "allowed": false,
      "paths": {
        "allowed": [],
        "disallowed": []
      }
    },
    {
      "name": "SuperBot",
      "allowed": false,
      "paths": {
        "allowed": [],
        "disallowed": []
      }
    },
    {
      "name": "SuperHTTP",
      "allowed": false,
      "paths": {
        "allowed": [],
        "disallowed": []
      }
    },
    {
      "name": "Surfbot",
      "allowed": false,
      "paths": {
        "allowed": [],
        "disallowed": []
      }
    },
    {
      "name": "Lydia",
      "allowed": false,
      "paths": {
        "allowed": [],
        "disallowed": []
      }
    },
    {
      "name": "Clearware",
      "allowed": false,
      "paths": {
        "allowed": [],
        "disallowed": []
      }
    },
    {
      "name": "ShablastBot",
      "allowed": false,
      "paths": {
        "allowed": [],
        "disallowed": []
      }
    },
    {
      "name": "BlitzBOT",
      "allowed": false,
      "paths": {
        "allowed": [],
        "disallowed": []
      }
    },
    {
      "name": "claudebot",
      "allowed": false,
      "paths": {
        "allowed": [],
        "disallowed": []
      }
    },
    {
      "name": "YandexBot",
      "allowed": false,
      "paths": {
        "allowed": [],
        "disallowed": []
      }
    },
    {
      "name": "2ip bot",
      "allowed": false,
      "paths": {
        "allowed": [],
        "disallowed": []
      }
    },
    {
      "name": "Scrapy",
      "allowed": false,
      "paths": {
        "allowed": [],
        "disallowed": []
      }
    },
    {
      "name": "DotBot",
      "allowed": false,
      "paths": {
        "allowed": [],
        "disallowed": []
      }
    },
    {
      "name": "bingbot",
      "allowed": false,
      "paths": {
        "allowed": [],
        "disallowed": []
      }
    },
    {
      "name": "OAI-SearchBot",
      "allowed": false,
      "paths": {
        "allowed": [],
        "disallowed": []
      }
    },
    {
      "name": "SentiBot",
      "allowed": false,
      "paths": {
        "allowed": [],
        "disallowed": []
      }
    },
    {
      "name": "MJ12bot",
      "allowed": false,
      "paths": {
        "allowed": [],
        "disallowed": []
      }
    },
    {
      "name": "SlySearch",
      "allowed": false,
      "paths": {
        "allowed": [],
        "disallowed": []
      }
    },
    {
      "name": "SmartDownload",
      "allowed": false,
      "paths": {
        "allowed": [],
        "disallowed": []
      }
    },
    {
      "name": "SpankBot",
      "allowed": false,
      "paths": {
        "allowed": [],
        "disallowed": []
      }
    },
    {
      "name": "spanner",
      "allowed": false,
      "paths": {
        "allowed": [],
        "disallowed": []
      }
    },
    {
      "name": "SuperBot",
      "allowed": false,
      "paths": {
        "allowed": [],
        "disallowed": []
      }
    },
    {
      "name": "SuperHTTP",
      "allowed": false,
      "paths": {
        "allowed": [],
        "disallowed": []
      }
    },
    {
      "name": "Surfbot",
      "allowed": false,
      "paths": {
        "allowed": [],
        "disallowed": []
      }
    },
    {
      "name": "Lydia",
      "allowed": false,
      "paths": {
        "allowed": [],
        "disallowed": []
      }
    },
    {
      "name": "Clearware",
      "allowed": false,
      "paths": {
        "allowed": [],
        "disallowed": []
      }
    },
    {
      "name": "ShablastBot",
      "allowed": false,
      "paths": {
        "allowed": [],
        "disallowed": []
      }
    },
    {
      "name": "BlitzBOT",
      "allowed": false,
      "paths": {
        "allowed": [],
        "disallowed": []
      }
    },
    {
      "name": "claudebot",
      "allowed": false,
      "paths": {
        "allowed": [],
        "disallowed": []
      }
    },
    {
      "name": "YandexBot",
      "allowed": false,
      "paths": {
        "allowed": [],
        "disallowed": []
      }
    },
    {
      "name": "2ip bot",
      "allowed": false,
      "paths": {
        "allowed": [],
        "disallowed": []
      }
    },
    {
      "name": "Scrapy",
      "allowed": false,
      "paths": {
        "allowed": [],
        "disallowed": []
      }
    },
    {
      "name": "DotBot",
      "allowed": false,
      "paths": {
        "allowed": [],
        "disallowed": []
      }
    },
    {
      "name": "bingbot",
      "allowed": false,
      "paths": {
        "allowed": [],
        "disallowed": []
      }
    },
    {
      "name": "OAI-SearchBot",
      "allowed": false,
      "paths": {
        "allowed": [],
        "disallowed": []
      }
    },
    {
      "name": "SentiBot",
      "allowed": false,
      "paths": {
        "allowed": [],
        "disallowed": []
      }
    },
    {
      "name": "MJ12bot",
      "allowed": false,
      "paths": {
        "allowed": [],
        "disallowed": []
      }
    }
  ],
  "stats": {
    "totalSpecificBots": 402,
    "allowedBots": 2,
    "disallowedBots": 400,
    "hasGlobalAllow": true
  },
  "bots": [
    {
      "name": "*",
      "allowed": true
    },
    {
      "name": "Googlebot",
      "allowed": true
    },
    {
      "name": "Twitterbot",
      "allowed": true
    },
    {
      "name": "SlySearch",
      "allowed": false
    },
    {
      "name": "SmartDownload",
      "allowed": false
    },
    {
      "name": "SpankBot",
      "allowed": false
    },
    {
      "name": "spanner",
      "allowed": false
    },
    {
      "name": "SuperBot",
      "allowed": false
    },
    {
      "name": "SuperHTTP",
      "allowed": false
    },
    {
      "name": "Surfbot",
      "allowed": false
    },
    {
      "name": "Lydia",
      "allowed": false
    },
    {
      "name": "Clearware",
      "allowed": false
    },
    {
      "name": "ShablastBot",
      "allowed": false
    },
    {
      "name": "BlitzBOT",
      "allowed": false
    },
    {
      "name": "claudebot",
      "allowed": false
    },
    {
      "name": "YandexBot",
      "allowed": false
    },
    {
      "name": "2ip bot",
      "allowed": false
    },
    {
      "name": "Scrapy",
      "allowed": false
    },
    {
      "name": "DotBot",
      "allowed": false
    },
    {
      "name": "bingbot",
      "allowed": false
    },
    {
      "name": "OAI-SearchBot",
      "allowed": false
    },
    {
      "name": "SentiBot",
      "allowed": false
    },
    {
      "name": "MJ12bot",
      "allowed": false
    },
    {
      "name": "SlySearch",
      "allowed": false
    },
    {
      "name": "SmartDownload",
      "allowed": false
    },
    {
      "name": "SpankBot",
      "allowed": false
    },
    {
      "name": "spanner",
      "allowed": false
    },
    {
      "name": "SuperBot",
      "allowed": false
    },
    {
      "name": "SuperHTTP",
      "allowed": false
    },
    {
      "name": "Surfbot",
      "allowed": false
    },
    {
      "name": "Lydia",
      "allowed": false
    },
    {
      "name": "Clearware",
      "allowed": false
    },
    {
      "name": "ShablastBot",
      "allowed": false
    },
    {
      "name": "BlitzBOT",
      "allowed": false
    },
    {
      "name": "claudebot",
      "allowed": false
    },
    {
      "name": "YandexBot",
      "allowed": false
    },
    {
      "name": "2ip bot",
      "allowed": false
    },
    {
      "name": "Scrapy",
      "allowed": false
    },
    {
      "name": "DotBot",
      "allowed": false
    },
    {
      "name": "bingbot",
      "allowed": false
    },
    {
      "name": "OAI-SearchBot",
      "allowed": false
    },
    {
      "name": "SentiBot",
      "allowed": false
    },
    {
      "name": "MJ12bot",
      "allowed": false
    },
    {
      "name": "SlySearch",
      "allowed": false
    },
    {
      "name": "SmartDownload",
      "allowed": false
    },
    {
      "name": "SpankBot",
      "allowed": false
    },
    {
      "name": "spanner",
      "allowed": false
    },
    {
      "name": "SuperBot",
      "allowed": false
    },
    {
      "name": "SuperHTTP",
      "allowed": false
    },
    {
      "name": "Surfbot",
      "allowed": false
    },
    {
      "name": "Lydia",
      "allowed": false
    },
    {
      "name": "Clearware",
      "allowed": false
    },
    {
      "name": "ShablastBot",
      "allowed": false
    },
    {
      "name": "BlitzBOT",
      "allowed": false
    },
    {
      "name": "claudebot",
      "allowed": false
    },
    {
      "name": "YandexBot",
      "allowed": false
    },
    {
      "name": "2ip bot",
      "allowed": false
    },
    {
      "name": "Scrapy",
      "allowed": false
    },
    {
      "name": "DotBot",
      "allowed": false
    },
    {
      "name": "bingbot",
      "allowed": false
    },
    {
      "name": "OAI-SearchBot",
      "allowed": false
    },
    {
      "name": "SentiBot",
      "allowed": false
    },
    {
      "name": "MJ12bot",
      "allowed": false
    },
    {
      "name": "SlySearch",
      "allowed": false
    },
    {
      "name": "SmartDownload",
      "allowed": false
    },
    {
      "name": "SpankBot",
      "allowed": false
    },
    {
      "name": "spanner",
      "allowed": false
    },
    {
      "name": "SuperBot",
      "allowed": false
    },
    {
      "name": "SuperHTTP",
      "allowed": false
    },
    {
      "name": "Surfbot",
      "allowed": false
    },
    {
      "name": "Lydia",
      "allowed": false
    },
    {
      "name": "Clearware",
      "allowed": false
    },
    {
      "name": "ShablastBot",
      "allowed": false
    },
    {
      "name": "BlitzBOT",
      "allowed": false
    },
    {
      "name": "claudebot",
      "allowed": false
    },
    {
      "name": "YandexBot",
      "allowed": false
    },
    {
      "name": "2ip bot",
      "allowed": false
    },
    {
      "name": "Scrapy",
      "allowed": false
    },
    {
      "name": "DotBot",
      "allowed": false
    },
    {
      "name": "bingbot",
      "allowed": false
    },
    {
      "name": "OAI-SearchBot",
      "allowed": false
    },
    {
      "name": "SentiBot",
      "allowed": false
    },
    {
      "name": "MJ12bot",
      "allowed": false
    },
    {
      "name": "SlySearch",
      "allowed": false
    },
    {
      "name": "SmartDownload",
      "allowed": false
    },
    {
      "name": "SpankBot",
      "allowed": false
    },
    {
      "name": "spanner",
      "allowed": false
    },
    {
      "name": "SuperBot",
      "allowed": false
    },
    {
      "name": "SuperHTTP",
      "allowed": false
    },
    {
      "name": "Surfbot",
      "allowed": false
    },
    {
      "name": "Lydia",
      "allowed": false
    },
    {
      "name": "Clearware",
      "allowed": false
    },
    {
      "name": "ShablastBot",
      "allowed": false
    },
    {
      "name": "BlitzBOT",
      "allowed": false
    },
    {
      "name": "claudebot",
      "allowed": false
    },
    {
      "name": "YandexBot",
      "allowed": false
    },
    {
      "name": "2ip bot",
      "allowed": false
    },
    {
      "name": "Scrapy",
      "allowed": false
    },
    {
      "name": "DotBot",
      "allowed": false
    },
    {
      "name": "bingbot",
      "allowed": false
    },
    {
      "name": "OAI-SearchBot",
      "allowed": false
    },
    {
      "name": "SentiBot",
      "allowed": false
    },
    {
      "name": "MJ12bot",
      "allowed": false
    },
    {
      "name": "SlySearch",
      "allowed": false
    },
    {
      "name": "SmartDownload",
      "allowed": false
    },
    {
      "name": "SpankBot",
      "allowed": false
    },
    {
      "name": "spanner",
      "allowed": false
    },
    {
      "name": "SuperBot",
      "allowed": false
    },
    {
      "name": "SuperHTTP",
      "allowed": false
    },
    {
      "name": "Surfbot",
      "allowed": false
    },
    {
      "name": "Lydia",
      "allowed": false
    },
    {
      "name": "Clearware",
      "allowed": false
    },
    {
      "name": "ShablastBot",
      "allowed": false
    },
    {
      "name": "BlitzBOT",
      "allowed": false
    },
    {
      "name": "claudebot",
      "allowed": false
    },
    {
      "name": "YandexBot",
      "allowed": false
    },
    {
      "name": "2ip bot",
      "allowed": false
    },
    {
      "name": "Scrapy",
      "allowed": false
    },
    {
      "name": "DotBot",
      "allowed": false
    },
    {
      "name": "bingbot",
      "allowed": false
    },
    {
      "name": "OAI-SearchBot",
      "allowed": false
    },
    {
      "name": "SentiBot",
      "allowed": false
    },
    {
      "name": "MJ12bot",
      "allowed": false
    },
    {
      "name": "SlySearch",
      "allowed": false
    },
    {
      "name": "SmartDownload",
      "allowed": false
    },
    {
      "name": "SpankBot",
      "allowed": false
    },
    {
      "name": "spanner",
      "allowed": false
    },
    {
      "name": "SuperBot",
      "allowed": false
    },
    {
      "name": "SuperHTTP",
      "allowed": false
    },
    {
      "name": "Surfbot",
      "allowed": false
    },
    {
      "name": "Lydia",
      "allowed": false
    },
    {
      "name": "Clearware",
      "allowed": false
    },
    {
      "name": "ShablastBot",
      "allowed": false
    },
    {
      "name": "BlitzBOT",
      "allowed": false
    },
    {
      "name": "claudebot",
      "allowed": false
    },
    {
      "name": "YandexBot",
      "allowed": false
    },
    {
      "name": "2ip bot",
      "allowed": false
    },
    {
      "name": "Scrapy",
      "allowed": false
    },
    {
      "name": "DotBot",
      "allowed": false
    },
    {
      "name": "bingbot",
      "allowed": false
    },
    {
      "name": "OAI-SearchBot",
      "allowed": false
    },
    {
      "name": "SentiBot",
      "allowed": false
    },
    {
      "name": "MJ12bot",
      "allowed": false
    },
    {
      "name": "SlySearch",
      "allowed": false
    },
    {
      "name": "SmartDownload",
      "allowed": false
    },
    {
      "name": "SpankBot",
      "allowed": false
    },
    {
      "name": "spanner",
      "allowed": false
    },
    {
      "name": "SuperBot",
      "allowed": false
    },
    {
      "name": "SuperHTTP",
      "allowed": false
    },
    {
      "name": "Surfbot",
      "allowed": false
    },
    {
      "name": "Lydia",
      "allowed": false
    },
    {
      "name": "Clearware",
      "allowed": false
    },
    {
      "name": "ShablastBot",
      "allowed": false
    },
    {
      "name": "BlitzBOT",
      "allowed": false
    },
    {
      "name": "claudebot",
      "allowed": false
    },
    {
      "name": "YandexBot",
      "allowed": false
    },
    {
      "name": "2ip bot",
      "allowed": false
    },
    {
      "name": "Scrapy",
      "allowed": false
    },
    {
      "name": "DotBot",
      "allowed": false
    },
    {
      "name": "bingbot",
      "allowed": false
    },
    {
      "name": "OAI-SearchBot",
      "allowed": false
    },
    {
      "name": "SentiBot",
      "allowed": false
    },
    {
      "name": "MJ12bot",
      "allowed": false
    },
    {
      "name": "SlySearch",
      "allowed": false
    },
    {
      "name": "SmartDownload",
      "allowed": false
    },
    {
      "name": "SpankBot",
      "allowed": false
    },
    {
      "name": "spanner",
      "allowed": false
    },
    {
      "name": "SuperBot",
      "allowed": false
    },
    {
      "name": "SuperHTTP",
      "allowed": false
    },
    {
      "name": "Surfbot",
      "allowed": false
    },
    {
      "name": "Lydia",
      "allowed": false
    },
    {
      "name": "Clearware",
      "allowed": false
    },
    {
      "name": "ShablastBot",
      "allowed": false
    },
    {
      "name": "BlitzBOT",
      "allowed": false
    },
    {
      "name": "claudebot",
      "allowed": false
    },
    {
      "name": "YandexBot",
      "allowed": false
    },
    {
      "name": "2ip bot",
      "allowed": false
    },
    {
      "name": "Scrapy",
      "allowed": false
    },
    {
      "name": "DotBot",
      "allowed": false
    },
    {
      "name": "bingbot",
      "allowed": false
    },
    {
      "name": "OAI-SearchBot",
      "allowed": false
    },
    {
      "name": "SentiBot",
      "allowed": false
    },
    {
      "name": "MJ12bot",
      "allowed": false
    },
    {
      "name": "SlySearch",
      "allowed": false
    },
    {
      "name": "SmartDownload",
      "allowed": false
    },
    {
      "name": "SpankBot",
      "allowed": false
    },
    {
      "name": "spanner",
      "allowed": false
    },
    {
      "name": "SuperBot",
      "allowed": false
    },
    {
      "name": "SuperHTTP",
      "allowed": false
    },
    {
      "name": "Surfbot",
      "allowed": false
    },
    {
      "name": "Lydia",
      "allowed": false
    },
    {
      "name": "Clearware",
      "allowed": false
    },
    {
      "name": "ShablastBot",
      "allowed": false
    },
    {
      "name": "BlitzBOT",
      "allowed": false
    },
    {
      "name": "claudebot",
      "allowed": false
    },
    {
      "name": "YandexBot",
      "allowed": false
    },
    {
      "name": "2ip bot",
      "allowed": false
    },
    {
      "name": "Scrapy",
      "allowed": false
    },
    {
      "name": "DotBot",
      "allowed": false
    },
    {
      "name": "bingbot",
      "allowed": false
    },
    {
      "name": "OAI-SearchBot",
      "allowed": false
    },
    {
      "name": "SentiBot",
      "allowed": false
    },
    {
      "name": "MJ12bot",
      "allowed": false
    },
    {
      "name": "SlySearch",
      "allowed": false
    },
    {
      "name": "SmartDownload",
      "allowed": false
    },
    {
      "name": "SpankBot",
      "allowed": false
    },
    {
      "name": "spanner",
      "allowed": false
    },
    {
      "name": "SuperBot",
      "allowed": false
    },
    {
      "name": "SuperHTTP",
      "allowed": false
    },
    {
      "name": "Surfbot",
      "allowed": false
    },
    {
      "name": "Lydia",
      "allowed": false
    },
    {
      "name": "Clearware",
      "allowed": false
    },
    {
      "name": "ShablastBot",
      "allowed": false
    },
    {
      "name": "BlitzBOT",
      "allowed": false
    },
    {
      "name": "claudebot",
      "allowed": false
    },
    {
      "name": "YandexBot",
      "allowed": false
    },
    {
      "name": "2ip bot",
      "allowed": false
    },
    {
      "name": "Scrapy",
      "allowed": false
    },
    {
      "name": "DotBot",
      "allowed": false
    },
    {
      "name": "bingbot",
      "allowed": false
    },
    {
      "name": "OAI-SearchBot",
      "allowed": false
    },
    {
      "name": "SentiBot",
      "allowed": false
    },
    {
      "name": "MJ12bot",
      "allowed": false
    },
    {
      "name": "SlySearch",
      "allowed": false
    },
    {
      "name": "SmartDownload",
      "allowed": false
    },
    {
      "name": "SpankBot",
      "allowed": false
    },
    {
      "name": "spanner",
      "allowed": false
    },
    {
      "name": "SuperBot",
      "allowed": false
    },
    {
      "name": "SuperHTTP",
      "allowed": false
    },
    {
      "name": "Surfbot",
      "allowed": false
    },
    {
      "name": "Lydia",
      "allowed": false
    },
    {
      "name": "Clearware",
      "allowed": false
    },
    {
      "name": "ShablastBot",
      "allowed": false
    },
    {
      "name": "BlitzBOT",
      "allowed": false
    },
    {
      "name": "claudebot",
      "allowed": false
    },
    {
      "name": "YandexBot",
      "allowed": false
    },
    {
      "name": "2ip bot",
      "allowed": false
    },
    {
      "name": "Scrapy",
      "allowed": false
    },
    {
      "name": "DotBot",
      "allowed": false
    },
    {
      "name": "bingbot",
      "allowed": false
    },
    {
      "name": "OAI-SearchBot",
      "allowed": false
    },
    {
      "name": "SentiBot",
      "allowed": false
    },
    {
      "name": "MJ12bot",
      "allowed": false
    },
    {
      "name": "SlySearch",
      "allowed": false
    },
    {
      "name": "SmartDownload",
      "allowed": false
    },
    {
      "name": "SpankBot",
      "allowed": false
    },
    {
      "name": "spanner",
      "allowed": false
    },
    {
      "name": "SuperBot",
      "allowed": false
    },
    {
      "name": "SuperHTTP",
      "allowed": false
    },
    {
      "name": "Surfbot",
      "allowed": false
    },
    {
      "name": "Lydia",
      "allowed": false
    },
    {
      "name": "Clearware",
      "allowed": false
    },
    {
      "name": "ShablastBot",
      "allowed": false
    },
    {
      "name": "BlitzBOT",
      "allowed": false
    },
    {
      "name": "claudebot",
      "allowed": false
    },
    {
      "name": "YandexBot",
      "allowed": false
    },
    {
      "name": "2ip bot",
      "allowed": false
    },
    {
      "name": "Scrapy",
      "allowed": false
    },
    {
      "name": "DotBot",
      "allowed": false
    },
    {
      "name": "bingbot",
      "allowed": false
    },
    {
      "name": "OAI-SearchBot",
      "allowed": false
    },
    {
      "name": "SentiBot",
      "allowed": false
    },
    {
      "name": "MJ12bot",
      "allowed": false
    },
    {
      "name": "SlySearch",
      "allowed": false
    },
    {
      "name": "SmartDownload",
      "allowed": false
    },
    {
      "name": "SpankBot",
      "allowed": false
    },
    {
      "name": "spanner",
      "allowed": false
    },
    {
      "name": "SuperBot",
      "allowed": false
    },
    {
      "name": "SuperHTTP",
      "allowed": false
    },
    {
      "name": "Surfbot",
      "allowed": false
    },
    {
      "name": "Lydia",
      "allowed": false
    },
    {
      "name": "Clearware",
      "allowed": false
    },
    {
      "name": "ShablastBot",
      "allowed": false
    },
    {
      "name": "BlitzBOT",
      "allowed": false
    },
    {
      "name": "claudebot",
      "allowed": false
    },
    {
      "name": "YandexBot",
      "allowed": false
    },
    {
      "name": "2ip bot",
      "allowed": false
    },
    {
      "name": "Scrapy",
      "allowed": false
    },
    {
      "name": "DotBot",
      "allowed": false
    },
    {
      "name": "bingbot",
      "allowed": false
    },
    {
      "name": "OAI-SearchBot",
      "allowed": false
    },
    {
      "name": "SentiBot",
      "allowed": false
    },
    {
      "name": "MJ12bot",
      "allowed": false
    },
    {
      "name": "SlySearch",
      "allowed": false
    },
    {
      "name": "SmartDownload",
      "allowed": false
    },
    {
      "name": "SpankBot",
      "allowed": false
    },
    {
      "name": "spanner",
      "allowed": false
    },
    {
      "name": "SuperBot",
      "allowed": false
    },
    {
      "name": "SuperHTTP",
      "allowed": false
    },
    {
      "name": "Surfbot",
      "allowed": false
    },
    {
      "name": "Lydia",
      "allowed": false
    },
    {
      "name": "Clearware",
      "allowed": false
    },
    {
      "name": "ShablastBot",
      "allowed": false
    },
    {
      "name": "BlitzBOT",
      "allowed": false
    },
    {
      "name": "claudebot",
      "allowed": false
    },
    {
      "name": "YandexBot",
      "allowed": false
    },
    {
      "name": "2ip bot",
      "allowed": false
    },
    {
      "name": "Scrapy",
      "allowed": false
    },
    {
      "name": "DotBot",
      "allowed": false
    },
    {
      "name": "bingbot",
      "allowed": false
    },
    {
      "name": "OAI-SearchBot",
      "allowed": false
    },
    {
      "name": "SentiBot",
      "allowed": false
    },
    {
      "name": "MJ12bot",
      "allowed": false
    },
    {
      "name": "SlySearch",
      "allowed": false
    },
    {
      "name": "SmartDownload",
      "allowed": false
    },
    {
      "name": "SpankBot",
      "allowed": false
    },
    {
      "name": "spanner",
      "allowed": false
    },
    {
      "name": "SuperBot",
      "allowed": false
    },
    {
      "name": "SuperHTTP",
      "allowed": false
    },
    {
      "name": "Surfbot",
      "allowed": false
    },
    {
      "name": "Lydia",
      "allowed": false
    },
    {
      "name": "Clearware",
      "allowed": false
    },
    {
      "name": "ShablastBot",
      "allowed": false
    },
    {
      "name": "BlitzBOT",
      "allowed": false
    },
    {
      "name": "claudebot",
      "allowed": false
    },
    {
      "name": "YandexBot",
      "allowed": false
    },
    {
      "name": "2ip bot",
      "allowed": false
    },
    {
      "name": "Scrapy",
      "allowed": false
    },
    {
      "name": "DotBot",
      "allowed": false
    },
    {
      "name": "bingbot",
      "allowed": false
    },
    {
      "name": "OAI-SearchBot",
      "allowed": false
    },
    {
      "name": "SentiBot",
      "allowed": false
    },
    {
      "name": "MJ12bot",
      "allowed": false
    },
    {
      "name": "SlySearch",
      "allowed": false
    },
    {
      "name": "SmartDownload",
      "allowed": false
    },
    {
      "name": "SpankBot",
      "allowed": false
    },
    {
      "name": "spanner",
      "allowed": false
    },
    {
      "name": "SuperBot",
      "allowed": false
    },
    {
      "name": "SuperHTTP",
      "allowed": false
    },
    {
      "name": "Surfbot",
      "allowed": false
    },
    {
      "name": "Lydia",
      "allowed": false
    },
    {
      "name": "Clearware",
      "allowed": false
    },
    {
      "name": "ShablastBot",
      "allowed": false
    },
    {
      "name": "BlitzBOT",
      "allowed": false
    },
    {
      "name": "claudebot",
      "allowed": false
    },
    {
      "name": "YandexBot",
      "allowed": false
    },
    {
      "name": "2ip bot",
      "allowed": false
    },
    {
      "name": "Scrapy",
      "allowed": false
    },
    {
      "name": "DotBot",
      "allowed": false
    },
    {
      "name": "bingbot",
      "allowed": false
    },
    {
      "name": "OAI-SearchBot",
      "allowed": false
    },
    {
      "name": "SentiBot",
      "allowed": false
    },
    {
      "name": "MJ12bot",
      "allowed": false
    },
    {
      "name": "SlySearch",
      "allowed": false
    },
    {
      "name": "SmartDownload",
      "allowed": false
    },
    {
      "name": "SpankBot",
      "allowed": false
    },
    {
      "name": "spanner",
      "allowed": false
    },
    {
      "name": "SuperBot",
      "allowed": false
    },
    {
      "name": "SuperHTTP",
      "allowed": false
    },
    {
      "name": "Surfbot",
      "allowed": false
    },
    {
      "name": "Lydia",
      "allowed": false
    },
    {
      "name": "Clearware",
      "allowed": false
    },
    {
      "name": "ShablastBot",
      "allowed": false
    },
    {
      "name": "BlitzBOT",
      "allowed": false
    },
    {
      "name": "claudebot",
      "allowed": false
    },
    {
      "name": "YandexBot",
      "allowed": false
    },
    {
      "name": "2ip bot",
      "allowed": false
    },
    {
      "name": "Scrapy",
      "allowed": false
    },
    {
      "name": "DotBot",
      "allowed": false
    },
    {
      "name": "bingbot",
      "allowed": false
    },
    {
      "name": "OAI-SearchBot",
      "allowed": false
    },
    {
      "name": "SentiBot",
      "allowed": false
    },
    {
      "name": "MJ12bot",
      "allowed": false
    },
    {
      "name": "SlySearch",
      "allowed": false
    },
    {
      "name": "SmartDownload",
      "allowed": false
    },
    {
      "name": "SpankBot",
      "allowed": false
    },
    {
      "name": "spanner",
      "allowed": false
    },
    {
      "name": "SuperBot",
      "allowed": false
    },
    {
      "name": "SuperHTTP",
      "allowed": false
    },
    {
      "name": "Surfbot",
      "allowed": false
    },
    {
      "name": "Lydia",
      "allowed": false
    },
    {
      "name": "Clearware",
      "allowed": false
    },
    {
      "name": "ShablastBot",
      "allowed": false
    },
    {
      "name": "BlitzBOT",
      "allowed": false
    },
    {
      "name": "claudebot",
      "allowed": false
    },
    {
      "name": "YandexBot",
      "allowed": false
    },
    {
      "name": "2ip bot",
      "allowed": false
    },
    {
      "name": "Scrapy",
      "allowed": false
    },
    {
      "name": "DotBot",
      "allowed": false
    },
    {
      "name": "bingbot",
      "allowed": false
    },
    {
      "name": "OAI-SearchBot",
      "allowed": false
    },
    {
      "name": "SentiBot",
      "allowed": false
    },
    {
      "name": "MJ12bot",
      "allowed": false
    },
    {
      "name": "SlySearch",
      "allowed": false
    },
    {
      "name": "SmartDownload",
      "allowed": false
    },
    {
      "name": "SpankBot",
      "allowed": false
    },
    {
      "name": "spanner",
      "allowed": false
    },
    {
      "name": "SuperBot",
      "allowed": false
    },
    {
      "name": "SuperHTTP",
      "allowed": false
    },
    {
      "name": "Surfbot",
      "allowed": false
    },
    {
      "name": "Lydia",
      "allowed": false
    },
    {
      "name": "Clearware",
      "allowed": false
    },
    {
      "name": "ShablastBot",
      "allowed": false
    },
    {
      "name": "BlitzBOT",
      "allowed": false
    },
    {
      "name": "claudebot",
      "allowed": false
    },
    {
      "name": "YandexBot",
      "allowed": false
    },
    {
      "name": "2ip bot",
      "allowed": false
    },
    {
      "name": "Scrapy",
      "allowed": false
    },
    {
      "name": "DotBot",
      "allowed": false
    },
    {
      "name": "bingbot",
      "allowed": false
    },
    {
      "name": "OAI-SearchBot",
      "allowed": false
    },
    {
      "name": "SentiBot",
      "allowed": false
    },
    {
      "name": "MJ12bot",
      "allowed": false
    }
  ],
  "paths": {
    "allowed": [],
    "disallowed": [
      "/index.php?id=*",
      "/typo3/",
      "/fileadmin/",
      "/kcs-test/*",
      "/hene-test/*"
    ]
  }
}