{
  "domain": "www.familotel.com",
  "normalizedDomain": "www.familotel.com",
  "robotsTxt": "User-Agent: *\nAllow: /\n\n# Folders\nDisallow: /typo3/\n\n# Parameters\nDisallow: /*?id=*               # non-speaking URLs\nDisallow: /*cHash               # no cHash\nDisallow: /*?booker    # no booker\nDisallow: /*tx_powermail_pi1    # no powermail thanks pages\nDisallow: /fileadmin/pdf/*    # nothing from this directory\nDisallow: /*?c[id_package]=*\nDisallow: /*?set_language=*\nAllow: /*/sitemap.xml*cHash\t# allow cHash for sitemaps\n\n# Sitemap\nSitemap: https://www.familotel.com/de/sitemap.xml\n",
  "globalRules": {
    "paths": {
      "allowed": [
        "/*/sitemap.xml*cHash\t# allow cHash for sitemaps"
      ],
      "disallowed": [
        "/typo3/",
        "/*?id=*               # non-speaking URLs",
        "/*cHash               # no cHash",
        "/*?booker    # no booker",
        "/*tx_powermail_pi1    # no powermail thanks pages",
        "/fileadmin/pdf/*    # nothing from this directory",
        "/*?c[id_package]=*",
        "/*?set_language=*"
      ]
    }
  },
  "specificBots": [],
  "stats": {
    "totalSpecificBots": 0,
    "allowedBots": 0,
    "disallowedBots": 0,
    "hasGlobalAllow": true
  },
  "bots": [
    {
      "name": "*",
      "allowed": true
    }
  ],
  "paths": {
    "allowed": [
      "/*/sitemap.xml*cHash\t# allow cHash for sitemaps"
    ],
    "disallowed": [
      "/typo3/",
      "/*?id=*               # non-speaking URLs",
      "/*cHash               # no cHash",
      "/*?booker    # no booker",
      "/*tx_powermail_pi1    # no powermail thanks pages",
      "/fileadmin/pdf/*    # nothing from this directory",
      "/*?c[id_package]=*",
      "/*?set_language=*"
    ]
  }
}