{
  "domain": "www.jaegermeister.de",
  "normalizedDomain": "www.jaegermeister.de",
  "robotsTxt": "User-Agent: *\nAllow: /\nDisallow: /exploration/night-embassy\n\nSitemap: https://www.jagermeister.com/sitemap.xml\n",
  "globalRules": {
    "paths": {
      "allowed": [],
      "disallowed": [
        "/exploration/night-embassy"
      ]
    }
  },
  "specificBots": [],
  "stats": {
    "totalSpecificBots": 0,
    "allowedBots": 0,
    "disallowedBots": 0,
    "hasGlobalAllow": true
  },
  "bots": [
    {
      "name": "*",
      "allowed": true
    }
  ],
  "paths": {
    "allowed": [],
    "disallowed": [
      "/exploration/night-embassy"
    ]
  }
}