{
  "domain": "www.ullstein.de",
  "normalizedDomain": "www.ullstein.de",
  "robotsTxt": "# robots.txt for https://www.ullstein.de/\n\nsitemap: https://www.ullstein.de/sitemaps-2-sitemap.xml\n\n# live - don't allow web crawlers to index frontend-only routes\n\nUser-agent: *\nDisallow: /search\nDisallow: /cart\nDisallow: /cookiePrefs\nDisallow: /newsletter/preferences\nDisallow: /newsletter/thanks\nDisallow: /gewinnspiele\n\nUser-agent: AhrefsBot\nDisallow: /\n\n",
  "globalRules": {
    "paths": {
      "allowed": [],
      "disallowed": [
        "/search",
        "/cart",
        "/cookiePrefs",
        "/newsletter/preferences",
        "/newsletter/thanks",
        "/gewinnspiele"
      ]
    }
  },
  "specificBots": [
    {
      "name": "AhrefsBot",
      "allowed": false,
      "paths": {
        "allowed": [],
        "disallowed": []
      }
    }
  ],
  "stats": {
    "totalSpecificBots": 1,
    "allowedBots": 0,
    "disallowedBots": 1,
    "hasGlobalAllow": true
  },
  "bots": [
    {
      "name": "*",
      "allowed": true
    },
    {
      "name": "AhrefsBot",
      "allowed": false
    }
  ],
  "paths": {
    "allowed": [],
    "disallowed": [
      "/search",
      "/cart",
      "/cookiePrefs",
      "/newsletter/preferences",
      "/newsletter/thanks",
      "/gewinnspiele"
    ]
  }
}