{
  "domain": "www.nissan.de",
  "normalizedDomain": "www.nissan.de",
  "robotsTxt": "User-agent: *\nDisallow: /tel*\nDisallow: *_jcr_content.logout.html\nDisallow: *jcr_content.logout.html\nDisallow: *jcr:content.proxy.json\nDisallow: *_jcr_content*\nDisallow: *jcr:content*\nDisallow: /*?*page*\nDisallow: /*?*size*\nDisallow: /*?*location*\nDisallow: *?modelSpecCode=*\nDisallow: *?query=*\nDisallow: /404*\n\nSitemap: https://www.nissan.de/index.pages-sitemap.xml",
  "globalRules": {
    "paths": {
      "allowed": [],
      "disallowed": [
        "/tel*",
        "*_jcr_content.logout.html",
        "*jcr_content.logout.html",
        "*jcr:content.proxy.json",
        "*_jcr_content*",
        "*jcr:content*",
        "/*?*page*",
        "/*?*size*",
        "/*?*location*",
        "*?modelSpecCode=*",
        "*?query=*",
        "/404*"
      ]
    }
  },
  "specificBots": [],
  "stats": {
    "totalSpecificBots": 0,
    "allowedBots": 0,
    "disallowedBots": 0,
    "hasGlobalAllow": true
  },
  "bots": [
    {
      "name": "*",
      "allowed": true
    }
  ],
  "paths": {
    "allowed": [],
    "disallowed": [
      "/tel*",
      "*_jcr_content.logout.html",
      "*jcr_content.logout.html",
      "*jcr:content.proxy.json",
      "*_jcr_content*",
      "*jcr:content*",
      "/*?*page*",
      "/*?*size*",
      "/*?*location*",
      "*?modelSpecCode=*",
      "*?query=*",
      "/404*"
    ]
  }
}